rospy-stubs/__init__.pyi
rospy-stubs/client.pyi
rospy-stubs/core.pyi
rospy-stubs/exceptions.pyi
rospy-stubs/logger_level_service_caller.pyi
rospy-stubs/msg.pyi
rospy-stubs/msproxy.pyi
rospy-stubs/names.pyi
rospy-stubs/numpy_msg.pyi
rospy-stubs/rosconsole.pyi
rospy-stubs/rostime.pyi
rospy-stubs/service.pyi
rospy-stubs/timer.pyi
rospy-stubs/topics.pyi
rospy-stubs/impl/__init__.pyi
rospy-stubs/impl/init.pyi
rospy-stubs/impl/masterslave.pyi
rospy-stubs/impl/paramserver.pyi
rospy-stubs/impl/registration.pyi
rospy-stubs/impl/rosout.pyi
rospy-stubs/impl/simtime.pyi
rospy-stubs/impl/statistics.pyi
rospy-stubs/impl/tcpros.pyi
rospy-stubs/impl/tcpros_base.pyi
rospy-stubs/impl/tcpros_pubsub.pyi
rospy-stubs/impl/tcpros_service.pyi
rospy-stubs/impl/transport.pyi
rospy-stubs/impl/udpros.pyi
rospy-stubs/impl/validators.pyi
rospy_nonlocalstubs-0.1.3.dist-info/LICENSE
rospy_nonlocalstubs-0.1.3.dist-info/METADATA
rospy_nonlocalstubs-0.1.3.dist-info/WHEEL
rospy_nonlocalstubs-0.1.3.dist-info/top_level.txt
rospy_nonlocalstubs-0.1.3.dist-info/RECORD
