Metadata-Version: 2.1
Name: rospy-nonlocalstubs
Version: 0.1.3
Summary: A hack to get your editor to recognise rospy functions without installing ros on your system.
Author-email: JJWRoeloffs <jelleroeloffs@gmail.com>
Project-URL: Homepage, https://github.com/JJWRoeloffs/rospy-nonlocalstubs
Project-URL: Bug Tracker, https://github.com/JJWRoeloffs/rospy-nonlocalstubs/issues
Classifier: Programming Language :: Python :: 3
Classifier: License :: OSI Approved :: Apache Software License
Classifier: Operating System :: OS Independent
Requires-Python: >=3.8
License-File: LICENSE
